automx2/__init__.py
automx2/config.py
automx2/database.py
automx2/ldap.py
automx2/model.py
automx2/server.py
automx2/util.py
automx2/generators/__init__.py
automx2/generators/apple.py
automx2/generators/mozilla.py
automx2/generators/outlook.py
automx2/views/__init__.py
automx2/views/autoconfig.py
automx2/views/autodiscover.py
automx2/views/initdb.py
automx2/views/mobileconfig.py
automx2/views/site.py
automx2-2025.1.1.dist-info/LICENSE
automx2-2025.1.1.dist-info/METADATA
automx2-2025.1.1.dist-info/WHEEL
automx2-2025.1.1.dist-info/top_level.txt
automx2-2025.1.1.dist-info/RECORD
