Metadata-Version: 2.2
Name: automx2
Version: 2025.1.1
Summary: Mail User Agent auto-configuration service
Author-email: Ralph Seichter <automx2@seichter.de>
Project-URL: Documentation, https://rseichter.github.io/automx2/
Project-URL: Issues, https://github.com/rseichter/automx2/issues
Project-URL: Source, https://github.com/rseichter/automx2
Keywords: autoconfig,mobileconfig,mua
Classifier: Development Status :: 5 - Production/Stable
Classifier: License :: OSI Approved :: GNU General Public License v3 or later (GPLv3+)
Classifier: Operating System :: OS Independent
Classifier: Programming Language :: Python :: 3.7
Classifier: Topic :: System :: Systems Administration
Classifier: Topic :: Utilities
Requires-Python: >=3.7
License-File: LICENSE
Requires-Dist: Flask-Migrate>=2.5.2
Requires-Dist: Flask-SQLAlchemy>=2.4.1
Requires-Dist: Flask>=1.1.1
Requires-Dist: ldap3>=2.6
